hitchpylibrarytoolkit/__init__.py
hitchpylibrarytoolkit/deploy.py
hitchpylibrarytoolkit/docgen.py
hitchpylibrarytoolkit/engine.py
hitchpylibrarytoolkit/envirotest.py
hitchpylibrarytoolkit/exceptions.py
hitchpylibrarytoolkit/project_docs.py
hitchpylibrarytoolkit/pyenv.py
hitchpylibrarytoolkit/toolkit.py
hitchpylibrarytoolkit-0.6.23.dist-info/LICENSE.txt
hitchpylibrarytoolkit-0.6.23.dist-info/METADATA
hitchpylibrarytoolkit-0.6.23.dist-info/WHEEL
hitchpylibrarytoolkit-0.6.23.dist-info/top_level.txt
hitchpylibrarytoolkit-0.6.23.dist-info/RECORD
