Metadata-Version: 2.1
Name: hitchpylibrarytoolkit
Version: 0.6.23
Summary: Build, test, documentation, linting, reformatting and specification code for hitch libraries.
Author-email: Colm O'Connor <colm.oconnor.github@gmail.com>
License: MIT
Project-URL: homepage, https://hitchdev.com/
Keywords: yaml
Classifier: Programming Language :: Python :: 3
Classifier: License :: OSI Approved :: MIT License
Classifier: Topic :: Software Development :: Libraries
Classifier: Natural Language :: English
Requires-Python: >=3.7.0
License-File: LICENSE.txt
Requires-Dist: hitchstory >=0.12.0
Requires-Dist: hitchrunpy >=0.11.3
Requires-Dist: icommandlib >=0.6.0
Requires-Dist: hitchbuild
Requires-Dist: dirtempl >=0.1.3
Requires-Dist: templex >=0.2.0
Requires-Dist: twine >=0.11.0
Requires-Dist: flake8 >=3.5.0
Requires-Dist: pip-tools >=6.12.3
Requires-Dist: gitpython
Requires-Dist: black
Requires-Dist: ipython
Requires-Dist: q >=2.6
Requires-Dist: wheel
Requires-Dist: click
Requires-Dist: tomli
